{
  "healing_druids": {
    "id": "healing_druids",
    "name": "Healing Druids",
    "chassisId": "ranged_frame",
    "componentIds": [
      "basic_bow",
      "druidic_rites"
    ],
    "tier": "mid",
    "minLearnedDomains": 2,
    "tags": [
      "ranged",
      "druid",
      "healing",
      "forest"
    ],
    "nativeFaction": "druid_circle",
    "costOverride": 31
  },
  "druid_wizard": {
    "id": "druid_wizard",
    "name": "Druid Wizard",
    "chassisId": "ranged_frame",
    "componentIds": [
      "druidic_missiles",
      "druidic_rites"
    ],
    "tier": "late",
    "minLearnedDomains": 3,
    "tags": [
      "druid",
      "magic",
      "nature",
      "ranged",
      "glass_cannon"
    ],
    "nativeFaction": "druid_circle",
    "costOverride": 50
  },
  "blowgun_skirmishers": {
    "id": "blowgun_skirmishers",
    "name": "Blowgun Skirmishers",
    "chassisId": "ranged_frame",
    "componentIds": [
      "blowgun",
      "simple_armor"
    ],
    "tier": "mid",
    "minLearnedDomains": 2,
    "tags": [
      "ranged",
      "poison",
      "stealth",
      "skirmish"
    ],
    "nativeFaction": "jungle_clan",
    "costOverride": 27
  },
  "serpent_priest": {
    "id": "serpent_priest",
    "name": "Serpent Priest",
    "chassisId": "ranged_frame",
    "componentIds": [
      "druidic_missiles",
      "venom_grenades",
      "jungle_mask"
    ],
    "tier": "late",
    "minLearnedDomains": 3,
    "tags": [
      "ranged",
      "poison",
      "magic",
      "stealth",
      "priest"
    ],
    "nativeFaction": "jungle_clan",
    "costOverride": 54
  },
  "fortress_archer": {
    "id": "fortress_archer",
    "name": "Fortress Archer",
    "chassisId": "ranged_frame",
    "componentIds": [
      "basic_bow",
      "fortress_training"
    ],
    "tier": "mid",
    "minLearnedDomains": 2,
    "tags": [
      "ranged",
      "fortress",
      "hill",
      "defensive"
    ],
    "nativeFaction": "hill_clan",
    "costOverride": 31
  },
  "steppe_raiders": {
    "id": "steppe_raiders",
    "name": "Steppe Raiders",
    "chassisId": "cavalry_frame",
    "componentIds": [
      "basic_spear",
      "skirmish_drill"
    ],
    "tier": "mid",
    "minLearnedDomains": 2,
    "tags": [
      "mounted",
      "raider"
    ],
    "nativeFaction": "steppe_clan",
    "costOverride": 38
  },
  "war_elephants": {
    "id": "war_elephants",
    "name": "War Elephants",
    "chassisId": "elephant_frame",
    "componentIds": [
      "basic_spear",
      "elephant_harness"
    ],
    "tier": "late",
    "minLearnedDomains": 3,
    "tags": [
      "mounted",
      "elephant",
      "shock"
    ],
    "nativeFaction": "savannah_lions",
    "costOverride": 61
  },
  "ice_defenders": {
    "id": "ice_defenders",
    "name": "Frost Reaver",
    "chassisId": "ranged_frame",
    "componentIds": [
      "basic_bow",
      "frost_forge",
      "cold_provisions"
    ],
    "tier": "mid",
    "minLearnedDomains": 2,
    "tags": [
      "ranged",
      "cold",
      "defensive",
      "endurance",
      "armor"
    ],
    "nativeFaction": "frost_wardens",
    "costOverride": 38
  },
  "steppe_priest": {
    "id": "steppe_priest",
    "name": "Steppe Priest",
    "chassisId": "infantry_frame",
    "componentIds": [
      "basic_spear",
      "simple_armor",
      "druidic_rites"
    ],
    "tier": "late",
    "minLearnedDomains": 3,
    "tags": [
      "infantry",
      "healing",
      "priest"
    ],
    "nativeFaction": "steppe_clan",
    "costOverride": 35
  },
  "catapult": {
    "id": "catapult",
    "name": "Catapult",
    "chassisId": "catapult_frame",
    "componentIds": [
      "catapult_arm",
      "fortress_training"
    ],
    "tier": "late",
    "minLearnedDomains": 3,
    "tags": [
      "ranged",
      "siege"
    ],
    "nativeFaction": "hill_clan",
    "costOverride": 50
  },
  "slaver": {
    "id": "slaver",
    "name": "Slaver",
    "chassisId": "heavy_infantry_frame",
    "componentIds": [
      "slaver_net",
      "simple_armor",
      "fortress_training",
      "musket"
    ],
    "tier": "mid",
    "minLearnedDomains": 2,
    "tags": [
      "heavy_infantry",
      "capture",
      "ranged"
    ],
    "nativeFaction": "coral_people",
    "costOverride": 43
  },
  "slave_galley": {
    "id": "slave_galley",
    "name": "Slave Galley",
    "chassisId": "galley_frame",
    "componentIds": [
      "slaver_net",
      "simple_armor"
    ],
    "tier": "late",
    "minLearnedDomains": 3,
    "tags": [
      "naval",
      "ranged",
      "transport",
      "capture"
    ],
    "nativeFaction": "coral_people",
    "costOverride": 39
  },
  "camel_lancers": {
    "id": "camel_lancers",
    "name": "Camel Lancers",
    "chassisId": "camel_frame",
    "componentIds": [
      "basic_spear",
      "desert_forged",
      "skirmish_drill"
    ],
    "tier": "mid",
    "minLearnedDomains": 2,
    "tags": [
      "camel",
      "desert"
    ],
    "nativeFaction": "desert_nomads",
    "costOverride": 35
  },
  "desert_immortals": {
    "id": "desert_immortals",
    "name": "Desert Immortals",
    "chassisId": "camel_frame",
    "componentIds": [
      "desert_forged",
      "desert_regen"
    ],
    "tier": "late",
    "minLearnedDomains": 3,
    "tags": [
      "camel",
      "mounted",
      "self_heal"
    ],
    "nativeFaction": "desert_nomads",
    "costOverride": 35,
    "movesBonus": -1
  },
  "war_chariot": {
    "id": "war_chariot",
    "name": "War Chariot",
    "chassisId": "chariot_frame",
    "componentIds": [
      "chariot_bow",
      "chariot_armor",
      "chariot_drill"
    ],
    "tier": "mid",
    "minLearnedDomains": 2,
    "tags": [
      "cavalry",
      "chariot",
      "shock"
    ],
    "nativeFaction": "savannah_lions",
    "costOverride": 43
  },
  "river_raiders": {
    "id": "river_raiders",
    "name": "River Raiders",
    "chassisId": "naval_frame",
    "componentIds": [
      "ship_cannon",
      "simple_armor",
      "rivercraft_training"
    ],
    "tier": "late",
    "minLearnedDomains": 3,
    "tags": [
      "naval",
      "amphibious"
    ],
    "nativeFaction": "river_people",
    "costOverride": 50
  },
  "river_priest": {
    "id": "river_priest",
    "name": "River Priest",
    "chassisId": "ranged_frame",
    "componentIds": [
      "basic_bow",
      "simple_armor",
      "cold_provisions"
    ],
    "tier": "mid",
    "minLearnedDomains": 2,
    "tags": [
      "ranged",
      "healing",
      "priest"
    ],
    "nativeFaction": "river_people",
    "costOverride": 31
  },
  "polar_priest": {
    "id": "polar_priest",
    "name": "Polar Priest",
    "chassisId": "heavy_infantry_frame",
    "componentIds": [
      "basic_spear",
      "frost_forge",
      "cold_provisions"
    ],
    "tier": "late",
    "minLearnedDomains": 3,
    "tags": [
      "heavy_infantry",
      "cold",
      "endurance",
      "priest"
    ],
    "nativeFaction": "frost_wardens",
    "costOverride": 54
  }
}